hat/util/first.py
hat/util/socket.py
hat/util/cron.py
hat/util/py.typed
hat/util/__init__.py
hat/util/sqlite3.py
hat/util/callback.py
hat/util/bytes.py
hat_util-0.6.20.dist-info/LICENSE
hat_util-0.6.20.dist-info/METADATA
hat_util-0.6.20.dist-info/WHEEL
hat_util-0.6.20.dist-info/RECORD
