Metadata-Version: 2.1
Name: hat-util
Version: 0.6.20
Summary: Hat utility library
License: Apache-2.0
Classifier: Programming Language :: Python :: 3
Classifier: License :: OSI Approved :: Apache Software License
Provides-Extra: dev
Requires-Dist: hat-doit ~=0.16.2; extra == 'dev'
Requires-Python: >=3.10
Project-URL: Homepage, http://hat-open.com
Project-URL: Repository, https://github.com/hat-open/hat-util.git
Project-URL: Documentation, http://hat-util.hat-open.com
